linkarchivetools/LICENSE
linkarchivetools/README.md
linkarchivetools/__init__.py
linkarchivetools/backup.py
linkarchivetools/db2feeds.py
linkarchivetools/db2json.py
linkarchivetools/dbanalyzer.py
linkarchivetools/dbfilter.py
linkarchivetools/dbmerge.py
linkarchivetools/json2db.py
linkarchivetools/tableconfig.py
linkarchivetools/utils/alchemysearch.py
linkarchivetools/utils/omnisearch.py
linkarchivetools/utils/reflected.py
linkarchivetools-0.1.16.dist-info/LICENSE
linkarchivetools-0.1.16.dist-info/METADATA
linkarchivetools-0.1.16.dist-info/WHEEL
linkarchivetools-0.1.16.dist-info/RECORD
