Metadata-Version: 2.1
Name: linkarchivetools
Version: 0.1.16
Summary: Link Archive Tools
License: GPL3
Author: Iwan Grozny
Author-email: renegat@renegat0x0.ddns.net
Requires-Python: >=3.10,<4.0
Classifier: License :: Other/Proprietary License
Classifier: Programming Language :: Python :: 3
Classifier: Programming Language :: Python :: 3.10
Classifier: Programming Language :: Python :: 3.11
Classifier: Programming Language :: Python :: 3.12
Requires-Dist: psycopg2-binary
Requires-Dist: python-dateutil (>=2.8.2,<3.0.0)
Requires-Dist: requests (>=2.32.5,<3.0.0)
Requires-Dist: sqlalchemy
Requires-Dist: sympy (>=1.13.2,<2.0.0)
Requires-Dist: webtoolkit (>=0.0.191,<0.0.192)
